<annotation>
	<folder>car</folder>
	<filename>car_180.png</filename>
	<path>C:\Users\mahir\Documents\Pycharm Python Programs\Image Retraining\Training Images\car\car_180.png</path>
	<source>
		<database>Unknown</database>
	</source>
	<size>
		<width>740</width>
		<height>340</height>
		<depth>3</depth>
	</size>
	<segmented>0</segmented>
	<object>
		<name>car</name>
		<pose>Unspecified</pose>
		<truncated>0</truncated>
		<difficult>0</difficult>
		<bndbox>
			<xmin>12</xmin>
			<ymin>44</ymin>
			<xmax>726</xmax>
			<ymax>296</ymax>
		</bndbox>
	</object>
</annotation>
