<annotation>
	<folder>bed</folder>
	<filename>bed_228.png</filename>
	<path>C:\Users\mahir\Documents\Pycharm Python Programs\Image Retraining\Training Images\bed\bed_228.png</path>
	<source>
		<database>Unknown</database>
	</source>
	<size>
		<width>460</width>
		<height>335</height>
		<depth>3</depth>
	</size>
	<segmented>0</segmented>
	<object>
		<name>bed</name>
		<pose>Unspecified</pose>
		<truncated>0</truncated>
		<difficult>0</difficult>
		<bndbox>
			<xmin>24</xmin>
			<ymin>47</ymin>
			<xmax>432</xmax>
			<ymax>300</ymax>
		</bndbox>
	</object>
</annotation>
