<annotation>
	<folder>car</folder>
	<filename>car_273.jpg</filename>
	<path>C:\Users\mahir\Documents\Pycharm Python Programs\Image Retraining\Training Images\car\car_273.jpg</path>
	<source>
		<database>Unknown</database>
	</source>
	<size>
		<width>3508</width>
		<height>2481</height>
		<depth>3</depth>
	</size>
	<segmented>0</segmented>
	<object>
		<name>car</name>
		<pose>Unspecified</pose>
		<truncated>0</truncated>
		<difficult>0</difficult>
		<bndbox>
			<xmin>45</xmin>
			<ymin>832</ymin>
			<xmax>3495</xmax>
			<ymax>2390</ymax>
		</bndbox>
	</object>
</annotation>
